aim_flask/__init__.py
aim_flask/Interpreter/__init__.py
aim_flask/Interpreter/interpreter.py
aim_flask/main.py
aim_flask/templates/index.html
aim_flask-1.0.10.dist-info/entry_points.txt
aim_flask-1.0.10.dist-info/LICENSE
aim_flask-1.0.10.dist-info/METADATA
aim_flask-1.0.10.dist-info/WHEEL
aim_flask-1.0.10.dist-info/RECORD
